joestools/__init__.py
joestools/ccu_jack.py
joestools/common.py
joestools/credauth.py
joestools/fhem_con.py
joestools/hue.py
joestools/interface.py
joestools/knx.py
joestools/lancom.py
joestools/misc.py
joestools/msh.py
joestools-0.0.7.dist-info/licenses/LICENSE
joestools-0.0.7.dist-info/METADATA
joestools-0.0.7.dist-info/WHEEL
joestools-0.0.7.dist-info/top_level.txt
joestools-0.0.7.dist-info/RECORD
