Metadata-Version: 2.4
Name: joestools
Version: 0.0.7
Summary: Tools for my home automation
Author-email: Jochen Mälzer <mishki@mishki.de>
Classifier: Programming Language :: Python :: 3
Classifier: License :: OSI Approved :: MIT License
Classifier: Operating System :: OS Independent
Requires-Python: >=3.7
License-File: LICENSE
Requires-Dist: beautifulsoup4>=4.12.2
Requires-Dist: fhem>=0.6.5
Requires-Dist: Flask>=2.2.2
Requires-Dist: Flask-HTTPAuth>=4.7.0
Requires-Dist: itsdangerous>=2.1.2
Requires-Dist: Jinja2>=3.1.2
Requires-Dist: lxml>=4.9.2
Requires-Dist: netmiko-mishki>=4.1.2.5
Requires-Dist: mysql-connector-python>=8.0.32
Requires-Dist: platformdirs>=2.6.2
Requires-Dist: requests>=2.28.2
Requires-Dist: typing_extensions>=4.4.0
Requires-Dist: urllib3>=1.26.14
Requires-Dist: Werkzeug>=2.2.2
Dynamic: license-file
